management_auth/__init__.py
management_auth/tokens.py
management_auth/urls.py
management_auth/views.py
management_auth/management/commands/login_as.py
django_management_auth-0.0.0.dist-info/LICENSE
django_management_auth-0.0.0.dist-info/WHEEL
django_management_auth-0.0.0.dist-info/METADATA
django_management_auth-0.0.0.dist-info/RECORD
