Metadata-Version: 2.1
Name: django-management-auth
Version: 0.0.0
Summary: Login to a Django application from a management command
Author: Jake Howard
Requires-Python: >=3.8
Classifier: Environment :: Web Environment
Classifier: Framework :: Django
Classifier: Intended Audience :: Developers
Classifier: License :: OSI Approved :: MIT License
Classifier: Operating System :: OS Independent
Classifier: Programming Language :: Python :: 3.8
Classifier: Programming Language :: Python :: 3.9
Classifier: Programming Language :: Python :: 3.10
Classifier: Programming Language :: Python :: 3.11
Classifier: Programming Language :: Python :: 3
Classifier: Programming Language :: Python
Classifier: Topic :: Internet :: WWW/HTTP
Classifier: Topic :: Software Development
Requires-Dist: Django>=3.0,<5.0
Requires-Dist: ruff==0.0.291 ; extra == "lint"
Requires-Dist: black==23.9.1 ; extra == "lint"
Requires-Dist: time_machine ; extra == "test"
Requires-Dist: hypothesis[django] ; extra == "test"
Provides-Extra: lint
Provides-Extra: test
